latex2py/__init__.py
latex2py/parser/LaTeX.g4
latex2py/parser/__init__.py
latex2py/parser/config.py
latex2py/parser/errors.py
latex2py/parser/gen/LaTeX.interp
latex2py/parser/gen/LaTeX.tokens
latex2py/parser/gen/LaTeXLexer.interp
latex2py/parser/gen/LaTeXLexer.py
latex2py/parser/gen/LaTeXLexer.tokens
latex2py/parser/gen/LaTeXListener.py
latex2py/parser/gen/LaTeXParser.py
latex2py/parser/parse.py
latex2py/parser/variables.py
latex2py-0.2.2.dist-info/LICENSE.txt
latex2py-0.2.2.dist-info/METADATA
latex2py-0.2.2.dist-info/WHEEL
latex2py-0.2.2.dist-info/RECORD
