Metadata-Version: 2.1
Name: latex2py
Version: 0.2.2
Summary: A lightweight LaTeX-to-Python parser
License: MIT
Author: Milo Knowles
Author-email: miloknowles97@gmail.com
Requires-Python: >=3.9,<4.0
Classifier: License :: OSI Approved :: MIT License
Classifier: Programming Language :: Python :: 3
Classifier: Programming Language :: Python :: 3.9
Classifier: Programming Language :: Python :: 3.10
Classifier: Programming Language :: Python :: 3.11
Classifier: Programming Language :: Python :: 3.12
Requires-Dist: antlr4-python3-runtime (==4.11)
